{
  "SAC": {
    "name": "SAC",
    "implementation": "stable_baselines3",
    "total_timesteps": 1500000,
    "rewards": [
      -3043.0,
      -2950.0,
      -2279.0,
      -1852.0,
      -1644.0,
      -1166.2,
      -1565.2,
      -1366.4,
      -1192.4,
      -953.0,
      -817.0,
      -743.0,
      -842.0,
      -449.0,
      -623.0,
      -400.0,
      -397.0,
      -529.0,
      -311.0,
      -502.0,
      -296.0,
      -346.0,
      -380.0,
      -27.0,
      -244.0,
      -140.0,
      -16.0,
      -239.0,
      -257.0,
      -374.0,
      -105.0,
      -146.0,
      -246.0,
      -150.0,
      66.0,
      -143.0,
      -89.0,
      -100.0,
      -195.0,
      -284.0,
      -247.0,
      -4.0,
      214.0,
      -98.0,
      -90.0,
      -87.0,
      2.0,
      -175.0,
      -93.0,
      -214.0,
      33.0,
      30.0,
      -74.0,
      102.0,
      76.0,
      -89.0,
      205.0,
      -104.0,
      -52.0,
      -67.0,
      -26.0,
      86.0,
      -108.0,
      -68.0,
      71.0,
      -17.0,
      208.0,
      -93.0,
      -8.0,
      -27.0,
      96.0,
      117.0,
      -216.0,
      -52.0,
      0.0,
      165.0,
      13.0,
      183.0,
      -61.0,
      3.0,
      113.0,
      82.0,
      -212.0,
      138.0,
      181.0,
      0.0,
      -13.0,
      -14.0,
      78.0,
      191.0,
      219.0,
      -121.0,
      7.0,
      -53.0,
      44.0,
      330.0,
      76.0,
      15.0,
      227.0,
      49.0,
      94.0,
      127.0,
      95.0,
      68.0,
      58.0,
      -110.0,
      -106.0,
      -42.0,
      231.0,
      122.0,
      139.0,
      71.0,
      -53.0,
      206.0,
      223.0,
      87.0,
      -6.0,
      27.0,
      65.0,
      14.0,
      -145.0,
      58.0,
      58.0,
      147.0,
      202.0,
      -50.0,
      -21.0,
      161.0,
      -142.0,
      120.0,
      -71.0,
      88.0,
      -75.0,
      34.0,
      45.0,
      -93.0,
      40.0,
      184.0,
      205.0,
      305.0,
      85.0,
      210.0,
      3.0,
      158.0,
      90.0,
      -25.0,
      -152.0,
      -126.0,
      157.0,
      97.0,
      -164.0,
      -17.0,
      -84.0,
      229.0,
      -20.0,
      59.0,
      302.0,
      44.0,
      167.0,
      132.0,
      -203.0,
      218.0,
      18.0,
      -62.0,
      227.0,
      -6.0,
      72.0,
      -3.0,
      40.0,
      111.2,
      -99.8,
      54.0,
      22.0,
      44.0,
      118.0,
      162.0,
      313.0,
      86.0,
      -243.0,
      22.0,
      -5.0,
      -55.4,
      -27.6,
      3.0,
      150.0,
      -35.0,
      23.0,
      73.0,
      -144.0,
      -74.0,
      105.4,
      180.0,
      105.0,
      80.0,
      159.4,
      -12.0,
      -67.0,
      -5.0,
      134.0,
      -144.0,
      -41.8,
      -181.4,
      261.0,
      -51.0,
      -110.0,
      23.0,
      27.0,
      287.0,
      23.0,
      129.0,
      114.0,
      10.0,
      -80.0,
      230.0,
      144.0,
      77.0,
      105.0,
      -115.0,
      -156.0,
      132.0,
      37.0,
      362.0,
      94.0,
      39.0,
      70.0,
      134.0,
      284.0,
      53.0,
      184.0,
      198.0,
      85.0,
      81.0,
      29.0,
      229.0,
      80.0,
      184.0,
      234.0,
      -83.0,
      219.0,
      118.0,
      346.0,
      -1.0,
      150.0,
      36.0,
      75.0,
      288.0,
      114.0,
      103.0,
      50.0,
      138.0,
      52.0,
      194.0,
      10.0,
      288.0,
      220.0,
      262.0,
      237.0,
      34.0,
      226.0,
      202.0,
      95.0,
      166.0,
      104.0,
      59.0,
      160.0,
      -5.0,
      70.0,
      187.0,
      130.0,
      -97.0,
      274.0,
      53.0,
      270.0,
      192.0,
      -50.0,
      153.0,
      -7.0,
      34.0,
      182.0,
      278.0,
      143.0,
      156.0,
      167.0,
      129.0,
      338.0,
      120.0,
      197.0,
      83.0,
      249.0,
      134.0,
      243.0,
      -16.0,
      -140.0,
      86.0,
      36.0,
      -10.0,
      116.0,
      212.0,
      165.0,
      43.0,
      156.0,
      69.0,
      -24.0,
      205.0,
      110.0,
      -139.0,
      109.0,
      245.0,
      11.0,
      48.0,
      -18.0,
      86.0,
      145.0,
      179.0,
      182.0,
      248.0,
      -41.0,
      200.0,
      51.0,
      29.0,
      87.0,
      -95.0,
      16.0,
      144.0,
      -9.0,
      136.0,
      96.0,
      29.0,
      291.0,
      -63.0,
      207.0,
      63.0,
      -264.0,
      123.0,
      242.0,
      100.0,
      202.0,
      129.0,
      -46.0,
      125.0,
      177.0,
      -18.0,
      23.0,
      246.0,
      73.0,
      94.0,
      51.0,
      98.0,
      -8.0,
      32.0,
      79.0,
      139.0,
      46.0,
      20.0,
      102.0,
      129.0,
      99.0,
      5.0,
      71.0,
      196.0,
      78.0,
      87.0,
      -66.0,
      91.0,
      72.0,
      90.0,
      81.0,
      270.0,
      91.0,
      87.0,
      18.0,
      19.0,
      205.0,
      195.0,
      11.0,
      -38.0,
      182.0,
      29.0,
      7.0,
      151.0,
      58.0,
      62.0,
      49.0,
      23.0,
      215.0,
      68.0,
      176.0,
      -45.0,
      71.0,
      10.0,
      -86.0,
      105.0,
      144.0,
      96.0,
      169.0,
      116.0,
      242.0,
      190.0,
      115.0,
      168.0,
      83.0,
      25.0,
      78.0,
      41.0,
      35.0,
      42.0,
      204.0,
      153.0,
      179.0,
      -47.0,
      -40.0,
      18.0,
      2.0,
      103.0,
      101.0,
      -147.0,
      -127.0,
      -37.0,
      70.0,
      124.0,
      137.0,
      21.0,
      35.0,
      76.0,
      22.0,
      14.0,
      161.0,
      103.0,
      186.0,
      82.0,
      119.0,
      219.0,
      47.0,
      -15.0,
      -28.0,
      -51.0,
      -15.0,
      68.0,
      -15.0,
      193.0,
      114.0,
      38.0,
      235.0,
      -148.0,
      243.0,
      -131.0,
      226.0,
      43.0,
      242.0,
      15.0,
      80.0,
      231.0,
      89.0,
      25.0,
      295.0,
      167.0,
      71.0,
      -20.0,
      142.0,
      0.0,
      17.0,
      56.0,
      -102.0,
      95.0,
      255.0,
      85.0,
      22.0,
      252.0,
      95.0,
      -37.0,
      77.0,
      52.0,
      140.0,
      43.0,
      142.0,
      148.0,
      -98.0,
      180.0,
      -17.0,
      257.0,
      68.0,
      124.0,
      -3.0,
      41.0,
      71.0,
      -9.0,
      238.0,
      168.0,
      177.0,
      166.0,
      239.0,
      167.0,
      68.0,
      131.0,
      104.0,
      133.0,
      55.0,
      -161.0,
      158.0,
      157.0,
      70.0,
      149.0,
      196.0,
      84.0,
      189.0,
      149.0,
      357.0,
      38.0,
      89.0,
      -138.0,
      44.0,
      90.0,
      39.0,
      -14.0,
      286.0,
      -6.0,
      305.0,
      29.0,
      -87.0,
      104.0,
      111.0,
      193.0,
      -136.0,
      51.0,
      -7.0,
      209.0,
      -36.0,
      -19.0,
      -1.0,
      132.0,
      69.0,
      154.0,
      -88.0,
      297.0,
      298.0,
      45.0,
      197.0,
      39.0,
      151.0,
      175.0,
      48.0,
      182.0,
      -35.0,
      121.0,
      -45.0,
      -20.0,
      148.0,
      159.0,
      66.0,
      22.0,
      157.0,
      159.0,
      280.0,
      194.0,
      6.0,
      163.0,
      188.0,
      182.0,
      120.0,
      149.0,
      -11.0,
      121.0,
      79.0,
      247.0,
      47.0,
      124.0,
      409.0,
      139.0,
      204.0,
      149.0,
      239.0,
      26.0,
      137.0,
      154.0,
      190.0,
      68.0,
      -12.0,
      193.0,
      -6.0,
      42.0,
      257.0,
      -19.0,
      203.0,
      136.0,
      46.0,
      132.0,
      171.0,
      183.0,
      205.0,
      -17.0,
      -80.0,
      171.0,
      28.0,
      178.0,
      110.0,
      -134.0,
      213.0,
      90.0,
      140.0,
      -50.0,
      -21.0,
      107.0,
      -34.0,
      74.0,
      90.0,
      27.0,
      162.0,
      153.0,
      -160.0,
      23.0,
      129.0,
      3.0,
      142.0,
      209.0,
      58.0,
      133.0,
      360.0,
      8.0,
      173.0,
      64.0,
      73.0,
      221.0,
      140.0,
      -7.0,
      -158.0,
      71.0,
      98.0,
      222.0,
      -46.0,
      -78.0,
      132.2,
      224.0,
      18.0,
      83.0,
      4.0,
      142.0,
      58.0,
      107.0,
      300.0,
      -160.0,
      254.0,
      99.0,
      203.0,
      113.0,
      -33.0,
      59.0,
      203.0,
      133.0,
      48.0,
      -92.0,
      -6.0,
      91.0,
      160.0,
      248.0,
      116.0,
      206.0,
      45.0,
      136.0,
      96.0,
      161.0,
      11.0,
      -2.0,
      32.0,
      -92.0,
      166.0,
      185.0,
      26.0,
      182.0,
      137.0,
      147.0,
      84.0,
      6.0,
      265.0,
      -331.0,
      273.0,
      159.0,
      171.0,
      -90.0,
      188.0,
      18.0,
      141.0,
      80.0,
      99.0,
      301.0,
      257.0,
      249.0,
      97.0,
      214.0,
      315.0,
      149.0,
      154.0,
      255.0,
      122.0,
      -113.0,
      88.0,
      11.0,
      289.0,
      268.0,
      72.0,
      286.0,
      158.0,
      76.0,
      92.0,
      109.0,
      331.0,
      251.0,
      76.0,
      222.0,
      343.0,
      351.0,
      146.0,
      190.0,
      173.0,
      75.0,
      108.0,
      287.0,
      178.0,
      -17.0,
      388.0,
      63.0,
      32.0,
      80.0,
      64.0,
      3.0,
      192.0,
      -16.0,
      56.0,
      94.0,
      214.0,
      -45.0,
      225.0,
      254.0,
      324.0,
      10.2,
      129.0,
      -52.0,
      156.0,
      242.0,
      182.0,
      -91.0,
      77.0,
      66.0,
      126.0,
      -40.0,
      151.0,
      106.0,
      161.0,
      83.0,
      185.0,
      176.0,
      283.0,
      223.0,
      171.0,
      241.0,
      30.0,
      62.0,
      332.0,
      -54.0,
      221.0,
      148.0,
      84.0,
      172.0,
      144.0,
      -41.0,
      108.0,
      242.0,
      291.0,
      139.0,
      120.0,
      20.0,
      59.0,
      261.0,
      214.0,
      75.0,
      192.0,
      -12.0,
      168.0,
      61.0,
      201.0,
      119.0,
      98.0,
      179.0,
      175.0,
      88.0,
      7.0,
      359.0,
      130.0,
      134.0,
      22.0,
      -49.0,
      -39.0,
      226.0,
      -7.0,
      251.0,
      -43.0,
      91.0,
      259.0,
      265.0,
      -12.0,
      271.0,
      -54.0,
      64.0,
      1.0,
      110.0,
      105.0,
      205.0,
      192.0,
      36.0,
      181.0,
      84.0,
      206.0,
      -37.0,
      81.0,
      193.0,
      165.0,
      -32.0,
      29.0,
      227.0,
      85.0,
      -12.0,
      283.0,
      -109.0,
      348.0,
      117.0,
      -2.0,
      139.0,
      105.0,
      259.0,
      142.0,
      133.0,
      178.0,
      112.0,
      163.0,
      208.0,
      166.0,
      -35.0,
      173.0,
      46.0,
      314.0,
      145.0,
      292.0,
      110.0,
      210.0,
      180.0,
      45.0,
      122.0,
      150.0,
      291.0,
      150.0,
      81.0,
      83.0,
      80.0,
      -10.0,
      79.0,
      -12.0,
      215.0,
      188.0,
      85.0,
      77.0,
      32.0,
      97.0,
      -53.0,
      -126.0,
      317.0,
      162.0,
      92.0,
      48.0,
      51.0,
      279.0,
      141.0,
      142.0,
      180.0,
      111.0,
      -8.0,
      -31.0,
      267.0,
      95.0,
      -10.0,
      204.0,
      100.0,
      116.0,
      373.0,
      292.0,
      52.0,
      192.0,
      122.0,
      164.0,
      148.0,
      102.0,
      97.0,
      237.0,
      -120.0,
      72.0,
      22.0,
      125.0,
      127.0,
      82.0,
      80.0,
      76.0,
      167.0,
      -20.0,
      63.0,
      173.0,
      88.0,
      133.0,
      335.0,
      150.0,
      0.0,
      5.0,
      144.0,
      131.0,
      192.0,
      71.0,
      149.0,
      228.0,
      377.0,
      93.0,
      248.0,
      289.0,
      4.0,
      25.0,
      2.0,
      37.0,
      363.0,
      60.0,
      112.0,
      146.0,
      69.0,
      119.0,
      308.0,
      129.0,
      46.0,
      105.0,
      59.0,
      91.0,
      -15.0,
      204.0,
      172.0,
      246.0,
      -63.0,
      231.0,
      275.0,
      91.0,
      151.0,
      74.0,
      130.0,
      -70.0,
      -1.0,
      61.0,
      100.0,
      241.0,
      -92.0,
      236.0,
      91.0,
      16.0,
      185.0,
      342.0,
      53.0,
      125.0,
      128.0,
      279.0,
      87.0,
      74.0,
      -67.0,
      120.0,
      165.0,
      89.0,
      290.0,
      78.0,
      224.0,
      246.0,
      235.0,
      247.0,
      58.0,
      133.0,
      49.0,
      289.0,
      155.0,
      45.0,
      131.0,
      345.0,
      56.0,
      41.0,
      -31.0,
      119.0,
      -81.0,
      269.0,
      173.0,
      304.0,
      164.0,
      149.0,
      49.0,
      -85.0,
      -144.0,
      115.0,
      69.0,
      24.0,
      154.0,
      195.0,
      66.0,
      -56.0,
      106.0,
      186.0,
      83.0,
      215.0,
      -114.0,
      25.0,
      -6.0,
      218.0,
      21.0,
      126.0,
      -36.0,
      72.0,
      158.0,
      265.0,
      81.0,
      -12.0,
      -22.0,
      -41.0,
      -41.0,
      104.0,
      108.0,
      70.0,
      36.0,
      -1928.0,
      145.0,
      -43.0,
      120.0,
      120.0,
      155.0,
      91.0,
      116.0,
      81.0,
      248.0,
      78.0,
      -54.0,
      -205.0,
      399.0,
      116.0,
      66.0,
      5.0,
      71.0,
      83.0,
      209.0,
      57.0,
      131.0,
      -16.0,
      -67.0,
      -32.0,
      33.0,
      157.0,
      -102.0,
      -18.0,
      -22.0,
      29.0,
      -54.0,
      -29.0,
      248.0,
      -30.0,
      174.0,
      201.0,
      186.0,
      11.0,
      115.0,
      222.0,
      132.0,
      101.0,
      213.0,
      89.0,
      193.0,
      -43.0,
      127.0,
      -13.0,
      -54.0,
      9.0,
      66.0,
      199.0,
      174.0,
      178.0,
      165.0,
      217.0,
      165.0,
      89.0,
      133.0,
      300.0,
      -29.0,
      292.0,
      231.0,
      101.0,
      251.0,
      193.0,
      128.0,
      25.0,
      98.0,
      193.0,
      -100.0,
      112.0,
      80.0,
      73.0,
      30.0,
      206.0,
      42.0,
      275.0,
      22.0,
      64.0,
      251.0,
      -43.0,
      117.0,
      273.0,
      96.0,
      -69.0,
      72.0,
      -46.0,
      133.0,
      107.0,
      158.0,
      124.0,
      241.0,
      -144.0,
      144.0,
      -119.0,
      -54.0,
      64.0,
      19.0,
      -31.0,
      42.0,
      114.0,
      -65.0,
      120.0,
      79.0,
      197.0,
      155.0,
      105.0,
      126.0,
      134.0,
      67.0,
      -79.0,
      46.0,
      140.0,
      75.0,
      255.0,
      215.0,
      85.0,
      133.0,
      171.0,
      204.0,
      126.0,
      177.0,
      -26.0,
      -70.0,
      169.0,
      67.0,
      141.0,
      272.0,
      197.0,
      2.0,
      126.0,
      185.0,
      233.0,
      211.0,
      -94.0,
      145.0,
      217.0,
      186.0,
      -100.0,
      234.0,
      115.0,
      311.0,
      78.0,
      -57.0,
      73.0,
      71.0,
      103.0,
      197.0,
      139.0,
      83.0,
      128.0,
      -45.0,
      5.0,
      -42.0,
      40.0,
      87.0,
      194.0,
      97.0,
      124.0,
      -175.0,
      142.0,
      212.0,
      111.0,
      111.0,
      136.2,
      -21.8,
      119.4,
      -333.0,
      170.2,
      108.0,
      -27.0,
      -139.0,
      197.0,
      295.0,
      -90.0,
      -45.0,
      -43.0,
      205.0,
      -3861.0,
      10.0,
      39.0,
      -29.0,
      -115.0,
      41.0,
      315.0,
      141.0,
      22.0,
      -95.0,
      33.0,
      176.0,
      33.0,
      111.0,
      140.0,
      105.0,
      232.0,
      324.0,
      218.0,
      -3200.0,
      -29.0,
      96.0,
      -4.0,
      221.0,
      65.0,
      45.0,
      63.0,
      172.0,
      -61.0,
      111.0,
      171.0,
      75.0,
      243.0,
      432.0,
      -13.0,
      288.0,
      -42.0,
      -241.0,
      131.0,
      131.0,
      231.0,
      279.0,
      41.0,
      -93.0,
      18.0,
      270.0,
      51.0,
      -189.0,
      -13.0,
      -8.0,
      15.0,
      204.0,
      -2584.0,
      28.0,
      36.0,
      286.0,
      154.0,
      72.0,
      91.0,
      -26.0,
      64.0,
      228.0,
      54.0,
      255.0,
      155.0,
      84.0,
      348.0,
      199.0,
      91.0,
      162.0,
      103.0,
      96.0,
      -70.0,
      193.0,
      126.0,
      39.0,
      119.0,
      194.0,
      146.0,
      45.0,
      -148.0,
      245.0,
      15.0,
      -40.0,
      56.0,
      63.0,
      78.0,
      241.0,
      165.0,
      210.0,
      217.0,
      100.0,
      23.0,
      101.0,
      151.0,
      47.0,
      191.0,
      -31.0,
      155.0,
      344.0,
      144.0,
      -138.0,
      290.0,
      103.0,
      202.0,
      -7.0,
      39.0,
      134.0,
      101.0,
      160.0,
      120.0,
      193.0,
      214.0,
      -88.0,
      224.0,
      -31.0,
      101.0,
      211.0,
      -3.0,
      34.0,
      146.0,
      266.0,
      61.0,
      3.0,
      232.0,
      -21.0,
      -66.0,
      173.0,
      197.0,
      -11.0,
      103.0,
      -125.0,
      63.0,
      237.0,
      77.0,
      51.0,
      101.0,
      30.0,
      79.0,
      507.0,
      -11.0,
      1.0,
      174.0,
      115.0,
      -59.0,
      1.0,
      37.0,
      60.0,
      65.0,
      98.0,
      -30.0,
      -9.0,
      -87.0,
      127.0,
      57.0,
      220.0,
      211.0,
      81.0,
      236.0,
      -93.0,
      -81.0,
      43.0,
      184.0,
      277.0,
      39.0,
      77.0,
      101.0,
      255.0,
      17.0,
      127.0,
      -102.0,
      30.0,
      103.0,
      -76.0,
      133.0,
      183.0,
      165.0,
      -67.0,
      107.0,
      -139.0,
      232.0,
      -27.0,
      145.0,
      -24.0,
      0.0,
      -1.0,
      96.0,
      23.0,
      133.0,
      -93.0,
      178.0,
      -76.0,
      230.0,
      107.0,
      57.0,
      56.0,
      27.0,
      54.0,
      417.0,
      21.0,
      137.0,
      -30.0,
      264.0,
      42.0,
      -425.0,
      257.0,
      116.0,
      235.0,
      141.0,
      -90.0,
      -2724.0,
      80.0,
      129.0,
      107.0,
      233.0,
      17.0,
      154.0,
      25.0,
      59.0,
      83.0,
      173.0,
      192.0,
      139.0,
      317.0,
      187.0,
      44.0,
      -82.0,
      236.0,
      442.0,
      170.0,
      66.0,
      38.0,
      151.0,
      -81.0,
      24.0,
      186.0,
      -118.0,
      177.0,
      60.0,
      100.0,
      312.0,
      189.0,
      171.0,
      181.0,
      79.0,
      -23.0,
      42.0,
      182.0,
      173.0,
      138.0,
      213.0,
      96.0,
      75.0,
      282.0,
      264.0,
      19.0,
      -113.0,
      26.0,
      -11.0,
      29.0,
      -141.0,
      255.0,
      65.0,
      -127.0,
      53.0,
      3.0,
      -14.0,
      206.0,
      49.0,
      65.0,
      11.0,
      91.0,
      -42.0,
      82.0,
      99.0,
      100.0,
      -37.0,
      175.0,
      135.0,
      118.0,
      0.0,
      2.0,
      -15.0,
      168.0,
      253.0,
      143.0,
      160.0,
      302.0,
      97.0,
      -58.0,
      152.0,
      28.0,
      -2890.0,
      180.0,
      187.0,
      114.0,
      144.0,
      203.0,
      146.0,
      -74.0,
      58.0,
      300.0,
      159.0,
      50.0,
      93.0,
      51.0,
      53.0,
      201.0,
      33.0,
      251.0,
      -51.0,
      18.0,
      130.0,
      232.0,
      122.0,
      141.0,
      -86.0,
      89.0,
      103.0,
      171.0,
      -48.0,
      -34.0,
      -122.0,
      196.0,
      206.0,
      29.0,
      237.0,
      5.0,
      -140.0,
      212.0,
      289.0,
      -12.0,
      177.0,
      77.0,
      68.0,
      293.0,
      165.0,
      355.0,
      33.0,
      74.0,
      -16.0,
      130.0,
      120.0,
      212.0,
      68.0,
      133.0,
      77.0,
      142.0,
      219.0,
      131.0,
      -42.0,
      141.0,
      73.0,
      87.0,
      255.0,
      104.0,
      -59.0,
      149.0,
      143.0,
      149.0,
      64.0,
      207.0,
      78.0,
      298.0,
      178.0,
      82.0,
      117.0,
      385.0,
      20.0,
      119.0,
      -29.0,
      11.0,
      22.0,
      349.0,
      164.0,
      -43.0,
      -109.0,
      170.0,
      113.0,
      131.0,
      168.0,
      42.0,
      319.0,
      203.0,
      220.0,
      303.0,
      162.0,
      65.0,
      229.0,
      -42.0,
      78.0,
      214.0,
      6.0,
      61.0,
      155.0,
      129.0,
      117.0,
      149.0,
      134.0,
      224.0,
      134.0,
      -94.0,
      141.0,
      37.0,
      -49.0,
      72.0,
      211.0,
      118.0,
      -22.0,
      167.0,
      130.0,
      -136.0,
      129.0,
      183.0,
      35.0,
      398.0,
      191.0,
      65.0,
      72.0,
      -33.0,
      98.0,
      79.0,
      142.0,
      157.0,
      257.0,
      300.0,
      194.0,
      25.0,
      191.0,
      363.0,
      171.0,
      123.0,
      102.0,
      59.0,
      243.0,
      56.0,
      162.0,
      -114.0,
      -4682.0,
      108.0,
      211.0,
      163.0,
      129.0,
      -32.0,
      93.0,
      182.0,
      168.0,
      181.0,
      95.0,
      188.0,
      82.0,
      -156.0,
      35.0,
      91.0,
      155.0,
      63.0,
      -418.0,
      74.0,
      272.0,
      124.0,
      102.0,
      141.0,
      68.0,
      -52.0,
      205.0,
      17.0,
      23.0,
      -196.0,
      -2075.0,
      383.0,
      -57.0,
      52.0,
      159.0,
      55.0,
      196.0,
      152.0,
      232.0,
      -37.0,
      162.0,
      48.0,
      285.0,
      205.0,
      304.0,
      -284.0,
      146.0,
      147.0,
      73.0,
      85.0,
      212.0,
      55.0,
      14.0,
      228.0,
      175.0,
      133.0,
      26.0,
      264.0,
      -13.0,
      -50.0,
      -24.0,
      -131.0,
      -15.0,
      19.0,
      -206.0,
      -62.0,
      2.0,
      -444.0,
      -570.0,
      -151.0,
      -54.0,
      100.0,
      121.0,
      64.0,
      -40.0,
      49.0,
      90.0,
      -43.0,
      64.0,
      214.0,
      99.0,
      -95.0,
      50.0,
      -25.0,
      6.0,
      -13.0,
      51.0,
      16.0,
      198.0,
      349.0,
      253.0,
      65.0,
      -86.0,
      98.0,
      57.0,
      -319.0,
      -104.0,
      -4.0,
      -2279.0,
      251.0,
      -56.0,
      -13.0,
      -37.0,
      97.0,
      -49.0,
      99.0,
      144.0,
      -38.0,
      16.0,
      30.0,
      -68.0,
      83.0,
      -70.0,
      73.0,
      -20.0,
      145.0,
      189.0,
      81.0,
      214.0,
      273.0,
      -1.0,
      230.0,
      131.0,
      57.0,
      -88.0,
      227.0,
      -84.0,
      118.0,
      184.0,
      149.0,
      221.0,
      176.0,
      -11.0,
      82.0,
      28.0,
      165.0,
      39.0,
      185.0,
      220.0,
      170.0,
      183.0,
      200.0,
      140.0,
      218.0,
      144.0,
      -32.0,
      143.0,
      202.0,
      263.0,
      130.0,
      102.0,
      -216.0,
      122.0,
      -66.0,
      66.0,
      45.0,
      93.0,
      -81.0,
      26.0,
      -4.0,
      55.0,
      219.0,
      71.0,
      22.0,
      160.0,
      298.0,
      245.0,
      20.0,
      114.0,
      -11.0,
      230.0,
      48.0,
      -167.0,
      -112.0,
      -40.0,
      101.0,
      153.0,
      161.0,
      -40.0,
      229.0,
      -231.0,
      241.0,
      -81.0,
      44.0,
      260.0,
      32.0,
      184.0,
      291.0,
      33.0,
      50.0,
      80.0,
      27.0,
      167.0,
      252.0,
      269.0,
      245.0,
      134.0,
      139.0,
      -879.0,
      242.0,
      218.0,
      184.0,
      172.0,
      -81.0,
      -252.0,
      155.0,
      115.0,
      257.0,
      -24.0,
      192.0,
      -6.0,
      -64.0,
      -24.0,
      203.0,
      123.0,
      36.0,
      241.0,
      144.0,
      208.0,
      190.0,
      -97.0,
      48.0,
      -37.0,
      51.0,
      98.0,
      -53.0,
      4.0,
      72.0,
      153.0,
      144.0,
      161.0,
      78.0,
      144.0,
      115.0,
      11.0,
      -103.0,
      164.0,
      59.0,
      168.0,
      46.0,
      44.0,
      15.0,
      168.0,
      202.0,
      136.0,
      -17.0,
      -94.0,
      218.0,
      91.0,
      151.0,
      81.0,
      220.0,
      190.0,
      328.0,
      103.0,
      18.0,
      329.0,
      0.0,
      127.0,
      37.0,
      32.0,
      90.0,
      287.0,
      -119.0,
      291.0,
      255.0,
      127.0,
      287.0,
      133.0,
      144.0,
      131.0,
      198.0,
      127.0,
      -27.0,
      -22.0,
      -2.0,
      279.0,
      245.0,
      217.0,
      385.0,
      271.0,
      114.0,
      146.0,
      -496.0,
      19.0,
      109.0,
      -98.0,
      -14.0,
      117.0,
      123.0,
      84.0,
      -5.0,
      154.0,
      111.0,
      326.0,
      144.0,
      16.0,
      84.0,
      98.0,
      243.0,
      125.0,
      91.0,
      157.0,
      -34.0,
      40.0,
      98.0,
      48.0,
      41.0,
      -138.0,
      185.0,
      178.0,
      43.0,
      107.0,
      53.0,
      127.0,
      78.0,
      20.0,
      -47.0,
      0.0,
      48.0,
      84.0,
      87.0,
      266.0,
      175.0,
      31.0,
      -34.0,
      -157.0,
      255.0,
      27.0,
      -59.0,
      43.0,
      247.0,
      -11.0,
      129.0,
      142.0,
      -163.0,
      77.0,
      -12.0,
      -79.0,
      158.0,
      157.0,
      35.0,
      97.0,
      44.0,
      83.0,
      111.0,
      167.0,
      127.0,
      76.0,
      103.0,
      93.0,
      -134.0,
      159.0,
      136.0,
      -45.0,
      -14.0,
      -160.0,
      -45.0,
      -16.0,
      170.0,
      257.0,
      99.0,
      245.0,
      5.0,
      53.0,
      -42.0,
      97.0,
      237.0,
      171.0,
      120.0,
      64.0,
      99.0,
      37.0,
      -154.0,
      -59.0,
      -10.0,
      -11.0,
      116.0,
      -121.0,
      -242.0,
      4.0,
      243.0,
      242.0,
      206.0,
      -149.0,
      166.0,
      2.0,
      263.0,
      46.0,
      5.0,
      195.0,
      290.0,
      -16.0,
      27.0,
      143.0,
      35.0,
      143.0,
      19.0,
      -37.0,
      192.0,
      149.0,
      -70.0,
      111.0,
      -19.0,
      182.0,
      1.0,
      327.0,
      52.0,
      26.0,
      195.0,
      27.0,
      219.0,
      20.0,
      141.0,
      45.0,
      120.0,
      12.0,
      159.0,
      213.0,
      174.0,
      -30.0,
      95.0,
      145.0,
      47.0,
      296.0,
      -33.0,
      12.0,
      67.0,
      82.0,
      237.0,
      74.0,
      75.0,
      265.0,
      24.0,
      236.0,
      13.0,
      -44.0,
      -190.0,
      205.0,
      18.0,
      79.0,
      105.0,
      -99.0,
      42.0,
      75.0,
      120.0,
      97.0,
      -100.0,
      179.0,
      265.0,
      73.0,
      213.0,
      150.0,
      187.0,
      51.0,
      215.0,
      107.0,
      166.0,
      -14.0,
      24.0,
      -8.0,
      60.0,
      -10.0,
      107.0,
      5.0,
      160.0,
      83.0,
      -13.0,
      198.0,
      -3710.0,
      -96.0,
      91.0,
      215.0,
      159.0,
      -222.0,
      12.0,
      130.0,
      95.0,
      22.0,
      -43.0,
      174.0,
      271.0,
      33.0,
      274.0,
      110.0,
      -107.0,
      -145.0,
      100.0,
      42.0,
      13.0,
      115.0,
      10.0,
      238.0,
      109.0,
      14.0,
      -56.0,
      -1229.0,
      -1492.0,
      351.0,
      82.0,
      89.0,
      41.0,
      182.0,
      72.0,
      -69.0,
      -30.0,
      263.0,
      325.0,
      29.0,
      63.0,
      -19.0,
      80.0,
      86.0,
      261.0,
      -477.0,
      149.0,
      55.0,
      -110.0,
      66.0,
      272.0,
      114.0,
      134.0,
      202.0,
      -35.0,
      260.0,
      -415.0,
      194.0,
      317.0,
      114.0,
      19.0,
      24.0,
      127.0,
      184.0,
      112.0,
      -66.0,
      256.0,
      -124.0,
      37.0,
      262.0,
      102.0,
      162.0,
      199.0,
      63.0,
      184.0,
      144.0,
      24.0,
      212.0,
      -24.0,
      -71.0,
      -35.0,
      -33.0,
      222.0,
      41.0,
      -11.0,
      -51.0,
      44.0,
      44.0,
      139.0,
      274.0,
      58.0,
      174.0,
      53.0,
      -122.0,
      -32.0,
      103.0,
      49.0,
      8.0,
      16.0,
      18.0,
      -27.0,
      45.0,
      112.0,
      322.0,
      92.0,
      168.0,
      -159.0,
      60.0,
      188.0,
      52.0,
      5.0,
      159.0,
      265.0,
      82.0,
      241.0,
      168.0,
      191.0,
      91.0,
      159.0,
      175.0,
      131.0,
      257.0,
      307.0,
      62.0,
      -10.0,
      118.0,
      180.0,
      51.0,
      277.0,
      112.0,
      112.0,
      91.0,
      -53.0,
      115.0,
      -1093.0,
      177.0,
      256.0,
      86.0,
      -2160.0,
      112.0,
      141.0,
      94.0,
      -38.0,
      211.0,
      110.0,
      78.0,
      112.0,
      -11.0,
      -80.0,
      135.0,
      75.0,
      61.0,
      178.0,
      301.0,
      192.0,
      47.0,
      326.0,
      71.0,
      45.0,
      158.0,
      146.0,
      167.0,
      144.0,
      129.0,
      -39.0,
      -3.0,
      57.0,
      86.0,
      14.0,
      126.0,
      100.0,
      89.0,
      -92.0,
      271.0,
      186.0,
      350.0,
      -100.0,
      125.0,
      120.0,
      261.0,
      245.0,
      158.0,
      243.0,
      111.0,
      69.0,
      84.0,
      176.0,
      97.0,
      96.0,
      218.0,
      121.0,
      -27.0,
      307.0,
      -48.0,
      154.0,
      78.0,
      313.0,
      32.0,
      55.0,
      139.0,
      138.0,
      67.0,
      162.0,
      165.0,
      25.0,
      250.0,
      231.0,
      346.0,
      108.0,
      217.0,
      134.0,
      95.0,
      170.0,
      72.0,
      98.0,
      199.0,
      84.0,
      -38.0,
      96.0,
      71.0,
      158.0,
      134.0,
      200.0,
      297.0,
      73.0,
      97.0,
      -50.0,
      139.0,
      193.0,
      110.0,
      214.0,
      315.0,
      160.0,
      212.0,
      29.0,
      215.0,
      164.0,
      184.0,
      71.0,
      126.0,
      117.0,
      186.0,
      96.0,
      106.0,
      -22.0,
      15.0,
      148.0,
      48.0,
      120.0,
      316.0,
      102.0,
      99.0,
      177.0,
      -73.0,
      355.0,
      104.0,
      86.0,
      100.0,
      10.0,
      96.0,
      342.0,
      116.0,
      -3500.0,
      127.0,
      -81.0,
      153.0,
      146.0,
      46.0,
      118.0,
      114.0,
      68.0,
      255.0,
      242.0,
      140.0,
      158.0,
      88.0,
      321.0,
      240.0,
      174.0,
      21.0,
      -11.0,
      233.0,
      188.0,
      79.0,
      211.0,
      109.0,
      50.0,
      101.0,
      39.0,
      49.0,
      63.0,
      98.0,
      111.0,
      361.0,
      153.0,
      235.0,
      20.0,
      84.0,
      276.0,
      130.0,
      39.0,
      -10.0,
      141.0,
      -224.0,
      207.0,
      43.0,
      -404.0,
      183.0,
      -25.0,
      158.0,
      326.0,
      137.0,
      -19.0,
      180.0,
      101.0,
      61.0,
      121.0,
      64.0,
      54.0,
      27.0,
      102.0,
      46.0,
      3.0,
      -56.0,
      175.0,
      182.0,
      136.0,
      106.0,
      211.0,
      167.0,
      469.0,
      155.0,
      222.0,
      156.0,
      -28.0,
      213.0,
      95.0,
      269.0,
      16.0,
      -6.0,
      154.0,
      225.0,
      82.0,
      135.0,
      -1.0,
      82.0,
      31.0,
      94.0,
      336.0,
      102.0,
      12.0,
      43.0,
      -44.0,
      171.0,
      133.0,
      133.0,
      199.0,
      -56.0,
      329.0,
      -26.0,
      104.0,
      -27.8,
      221.0,
      -96.8,
      -313.0,
      277.8,
      29.8,
      52.6,
      -14.4,
      -94.8,
      23.0,
      147.2,
      -2827.0,
      -40.8,
      -23.0,
      -12.8,
      -203.4,
      68.0,
      -53.0,
      176.0,
      -5.0,
      61.0,
      202.0,
      90.0,
      -62.0,
      118.0,
      29.0,
      40.0,
      141.0,
      144.0,
      47.0,
      -49.0,
      31.0,
      130.0,
      158.0,
      102.0,
      405.0,
      72.0,
      -29.0,
      206.0,
      286.0,
      -1072.0,
      115.0,
      -53.0,
      206.0,
      39.0,
      193.0,
      81.0,
      116.0,
      53.0,
      121.0,
      139.0,
      -1.0,
      136.0,
      94.0,
      139.0,
      27.0,
      96.0,
      143.0,
      98.0,
      127.0,
      131.0,
      166.0,
      258.0,
      204.0,
      214.0,
      299.0,
      302.0,
      184.0,
      55.0,
      273.0,
      146.0,
      32.0,
      -909.0,
      151.0,
      321.0,
      35.0,
      60.0,
      -70.0,
      117.0,
      40.0,
      -59.0,
      -127.0,
      107.0,
      102.0,
      5.0,
      106.0,
      201.0,
      171.0,
      170.0,
      271.0,
      240.0,
      -465.0,
      117.0,
      209.0,
      6.0,
      18.0,
      154.0,
      123.0,
      4.0,
      -24.0,
      132.0,
      71.0,
      184.0,
      93.0,
      250.0,
      43.0,
      345.0,
      161.0,
      79.0,
      83.0,
      346.0,
      77.0,
      120.0,
      197.0,
      303.0,
      81.0,
      72.0,
      -21.0,
      93.0,
      208.0,
      280.0,
      212.0,
      87.0,
      140.0,
      278.0,
      135.0,
      1.0,
      184.0,
      182.0,
      160.0,
      -85.0,
      49.0,
      266.0,
      -10.0,
      115.0,
      -558.0,
      88.0,
      -1829.0,
      213.0,
      21.0,
      153.0,
      -2.0,
      195.0,
      6.0,
      128.0,
      183.0,
      186.0,
      297.0,
      64.0,
      168.0,
      156.0,
      101.0,
      -1.0,
      19.0,
      254.0,
      121.0,
      146.0,
      30.0,
      122.0,
      194.0,
      207.0,
      91.0,
      230.0,
      82.0,
      -37.0,
      61.0,
      34.0,
      -36.0,
      155.0,
      72.0,
      -132.0,
      169.0,
      66.0,
      -83.0,
      81.0,
      158.0,
      60.0,
      220.0,
      6.0,
      140.0,
      59.0,
      106.0,
      240.0,
      173.0,
      165.0,
      -51.0,
      -5.0,
      303.0,
      194.0,
      -1013.0,
      -15.0,
      191.0,
      6.0,
      -90.0,
      17.0,
      131.0,
      167.0,
      97.0,
      140.0,
      127.0,
      152.0,
      273.0,
      263.0,
      15.0,
      116.0,
      -966.0,
      79.0,
      -87.0,
      76.0,
      149.0,
      -47.0,
      -92.0,
      146.0,
      48.0,
      94.0,
      61.0,
      242.0,
      159.0,
      -63.0,
      -15.0,
      121.0,
      264.0,
      280.0,
      155.0,
      167.0,
      90.0,
      117.0,
      59.0,
      161.0,
      119.0,
      47.6,
      23.0,
      162.4,
      62.4,
      151.0,
      -369.0,
      205.0,
      263.0,
      198.0,
      -13.0,
      253.0,
      -3.0,
      76.0,
      112.0,
      -18.0,
      184.0,
      265.0,
      113.6,
      10.0,
      -123.0,
      -30.0,
      60.0,
      311.0,
      256.0,
      63.0,
      -50.0,
      24.0,
      245.0,
      158.0,
      94.0,
      124.0,
      111.0,
      106.0,
      14.0,
      2.0,
      73.0,
      230.0,
      194.0,
      -92.0,
      124.0,
      -6.0,
      6.0,
      230.0,
      79.0,
      -30.0,
      11.0,
      13.0,
      -142.0,
      216.0,
      178.0,
      157.0,
      167.0,
      182.0,
      159.0,
      128.0,
      -52.0,
      56.0,
      -15.0,
      20.0,
      75.0,
      71.0,
      75.0,
      138.0,
      170.0,
      103.0,
      -7.0,
      187.0,
      334.0,
      -64.0,
      356.0,
      -8.0,
      -24.0,
      94.0,
      61.0,
      241.0,
      253.0,
      68.0,
      89.0,
      76.0,
      170.0,
      163.0,
      49.0,
      -128.0,
      -205.0,
      223.0,
      -79.0,
      -106.0,
      104.0,
      0.0,
      249.0,
      188.0,
      -1085.0,
      241.0,
      82.0,
      246.0,
      229.0,
      62.0,
      167.0,
      264.0,
      -57.0,
      87.0,
      181.0,
      20.0,
      59.0,
      106.0,
      152.0,
      93.0,
      -78.0,
      191.0,
      -50.0,
      116.0,
      215.0,
      -75.0,
      202.0,
      -70.0,
      65.0,
      -146.0,
      114.0,
      45.0,
      53.0,
      129.0,
      34.0,
      170.0,
      85.0,
      -21.0,
      55.0,
      54.0,
      58.0,
      178.0,
      241.0,
      -260.0,
      36.0,
      84.0,
      94.0,
      -75.0,
      -9.0,
      -15.0,
      88.0,
      149.0,
      260.0,
      73.0,
      192.0,
      127.0,
      12.0,
      104.0,
      11.0,
      4.0,
      -12.0,
      237.0,
      144.0,
      -7.0,
      354.0,
      28.0,
      -294.0,
      109.0,
      335.0,
      235.0,
      159.0,
      249.0,
      101.0,
      108.0,
      196.0,
      271.0,
      310.0,
      -85.0,
      159.0,
      66.0,
      37.0,
      151.0,
      -152.0,
      73.0,
      3.0,
      246.0,
      -12.0,
      327.0,
      35.0,
      183.0,
      125.0,
      208.0,
      315.0,
      107.0,
      -73.0,
      179.0,
      5.0,
      261.0,
      204.0,
      206.0,
      96.0,
      -74.0,
      238.0,
      8.0,
      373.0,
      -12.0,
      168.0,
      94.0,
      109.0,
      35.0,
      192.0,
      116.0,
      18.0,
      60.0,
      157.0,
      60.0,
      50.0,
      178.0,
      86.0,
      -103.0,
      175.0,
      144.0,
      10.0,
      -24.0,
      8.0,
      131.0,
      -15.0,
      146.0,
      85.0,
      247.0,
      154.0,
      215.0,
      136.0,
      178.0,
      -2463.0,
      155.0,
      42.0,
      15.0,
      223.0,
      -10.0,
      -496.0,
      128.0,
      112.0,
      368.0,
      49.0,
      464.0,
      272.0,
      119.0,
      184.0,
      175.0,
      -20.0,
      -1.0,
      231.0,
      258.0,
      281.0,
      96.0,
      145.0,
      -63.0,
      150.0,
      129.0,
      50.0,
      80.0,
      334.0,
      39.0,
      -127.0,
      74.0,
      -74.0,
      278.0,
      233.0,
      118.0,
      -51.0,
      -91.0,
      17.0,
      -92.0,
      185.0,
      184.0,
      223.0,
      214.0,
      109.0,
      -20.0,
      -38.0,
      132.0,
      203.0,
      71.0,
      86.0,
      62.0,
      101.0,
      201.0,
      251.0,
      62.0,
      22.0,
      -128.0,
      -6.0,
      -84.0,
      151.0,
      122.0,
      57.0,
      149.0,
      8.0,
      129.0,
      131.0,
      336.0,
      128.0,
      167.0,
      77.0,
      140.0,
      139.0,
      128.0,
      48.0,
      -70.0,
      86.0
    ],
    "steps": [
      500,
      500,
      500,
      500,
      500,
      500,
      500,
      500,
      500,
      500,
      500,
      500,
      500,
      500,
      500,
      500,
      500,
      500,
      500,
      500,
      500,
      500,
      500,
      500,
      500,
      500,
      500,
      500,
      500,
      500,
      500,
      500,
      500,
      500,
      500,
      500,
      500,
      500,
      500,
      500,
      500,
      500,
      500,
      500,
      500,
      500,
      500,
      500,
      500,
      500,
      500,
      500,
      500,
      500,
      500,
      500,
      500,
      500,
      500,
      500,
      500,
      500,
      500,
      500,
      500,
      500,
      500,
      500,
      500,
      500,
      500,
      500,
      500,
      500,
      500,
      500,
      500,
      500,
      500,
      500,
      500,
      500,
      500,
      500,
      500,
      500,
      500,
      500,
      500,
      500,
      500,
      500,
      500,
      500,
      500,
      500,
      500,
      500,
      500,
      500,
      500,
      500,
      500,
      500,
      500,
      500,
      500,
      500,
      500,
      500,
      500,
      500,
      500,
      500,
      500,
      500,
      500,
      500,
      500,
      500,
      500,
      500,
      500,
      500,
      500,
      500,
      500,
      500,
      500,
      500,
      500,
      500,
      500,
      500,
      500,
      500,
      500,
      500,
      500,
      500,
      500,
      500,
      500,
      500,
      500,
      500,
      500,
      500,
      500,
      500,
      500,
      500,
      500,
      500,
      500,
      500,
      500,
      500,
      500,
      500,
      500,
      500,
      500,
      500,
      500,
      500,
      500,
      500,
      500,
      500,
      500,
      500,
      500,
      500,
      500,
      500,
      500,
      500,
      500,
      500,
      500,
      500,
      500,
      500,
      500,
      500,
      500,
      500,
      500,
      500,
      500,
      500,
      500,
      500,
      500,
      500,
      500,
      500,
      500,
      500,
      500,
      500,
      500,
      500,
      500,
      500,
      500,
      500,
      500,
      500,
      500,
      500,
      500,
      500,
      500,
      500,
      500,
      500,
      500,
      500,
      500,
      500,
      500,
      500,
      500,
      500,
      500,
      500,
      500,
      500,
      500,
      500,
      500,
      500,
      500,
      500,
      500,
      500,
      500,
      500,
      500,
      500,
      500,
      500,
      500,
      500,
      500,
      500,
      500,
      500,
      500,
      500,
      500,
      500,
      500,
      500,
      500,
      500,
      500,
      500,
      500,
      500,
      500,
      500,
      500,
      500,
      500,
      500,
      500,
      500,
      500,
      500,
      500,
      500,
      500,
      500,
      500,
      500,
      500,
      500,
      500,
      500,
      500,
      500,
      500,
      500,
      500,
      500,
      500,
      500,
      500,
      500,
      500,
      500,
      500,
      500,
      500,
      500,
      500,
      500,
      500,
      500,
      500,
      500,
      500,
      500,
      500,
      500,
      500,
      500,
      500,
      500,
      500,
      500,
      500,
      500,
      500,
      500,
      500,
      500,
      500,
      500,
      500,
      500,
      500,
      500,
      500,
      500,
      500,
      500,
      500,
      500,
      500,
      500,
      500,
      500,
      500,
      500,
      500,
      500,
      500,
      500,
      500,
      500,
      500,
      500,
      500,
      500,
      500,
      500,
      500,
      500,
      500,
      500,
      500,
      500,
      500,
      500,
      500,
      500,
      500,
      500,
      500,
      500,
      500,
      500,
      500,
      500,
      500,
      500,
      500,
      500,
      500,
      500,
      500,
      500,
      500,
      500,
      500,
      500,
      500,
      500,
      500,
      500,
      500,
      500,
      500,
      500,
      500,
      500,
      500,
      500,
      500,
      500,
      500,
      500,
      500,
      500,
      500,
      500,
      500,
      500,
      500,
      500,
      500,
      500,
      500,
      500,
      500,
      500,
      500,
      500,
      500,
      500,
      500,
      500,
      500,
      500,
      500,
      500,
      500,
      500,
      500,
      500,
      500,
      500,
      500,
      500,
      500,
      500,
      500,
      500,
      500,
      500,
      500,
      500,
      500,
      500,
      500,
      500,
      500,
      500,
      500,
      500,
      500,
      500,
      500,
      500,
      500,
      500,
      500,
      500,
      500,
      500,
      500,
      500,
      500,
      500,
      500,
      500,
      500,
      500,
      500,
      500,
      500,
      500,
      500,
      500,
      500,
      500,
      500,
      500,
      500,
      500,
      500,
      500,
      500,
      500,
      500,
      500,
      500,
      500,
      500,
      500,
      500,
      500,
      500,
      500,
      500,
      500,
      500,
      500,
      500,
      500,
      500,
      500,
      500,
      500,
      500,
      500,
      500,
      500,
      500,
      500,
      500,
      500,
      500,
      500,
      500,
      500,
      500,
      500,
      500,
      500,
      500,
      500,
      500,
      500,
      500,
      500,
      500,
      500,
      500,
      500,
      500,
      500,
      500,
      500,
      500,
      500,
      500,
      500,
      500,
      500,
      500,
      500,
      500,
      500,
      500,
      500,
      500,
      500,
      500,
      500,
      500,
      500,
      500,
      500,
      500,
      500,
      500,
      500,
      500,
      500,
      500,
      500,
      500,
      500,
      500,
      500,
      500,
      500,
      500,
      500,
      500,
      500,
      500,
      500,
      500,
      500,
      500,
      500,
      500,
      500,
      500,
      500,
      500,
      500,
      500,
      500,
      500,
      500,
      500,
      500,
      500,
      500,
      500,
      500,
      500,
      500,
      500,
      500,
      500,
      500,
      500,
      500,
      500,
      500,
      500,
      500,
      500,
      500,
      500,
      500,
      500,
      500,
      500,
      500,
      500,
      500,
      500,
      500,
      500,
      500,
      500,
      500,
      500,
      500,
      500,
      500,
      500,
      500,
      500,
      500,
      500,
      500,
      500,
      500,
      500,
      500,
      500,
      500,
      500,
      500,
      500,
      500,
      500,
      500,
      500,
      500,
      500,
      500,
      500,
      500,
      500,
      500,
      500,
      500,
      500,
      500,
      500,
      500,
      500,
      500,
      500,
      500,
      500,
      500,
      500,
      500,
      500,
      500,
      500,
      500,
      500,
      500,
      500,
      500,
      500,
      500,
      500,
      500,
      500,
      500,
      500,
      500,
      500,
      500,
      500,
      500,
      500,
      500,
      500,
      500,
      500,
      500,
      500,
      500,
      500,
      500,
      500,
      500,
      500,
      500,
      500,
      500,
      500,
      500,
      500,
      500,
      500,
      500,
      500,
      500,
      500,
      500,
      500,
      500,
      500,
      500,
      500,
      500,
      500,
      500,
      500,
      500,
      500,
      500,
      500,
      500,
      500,
      500,
      500,
      500,
      500,
      500,
      500,
      500,
      500,
      500,
      500,
      500,
      500,
      500,
      500,
      500,
      500,
      500,
      500,
      500,
      500,
      500,
      500,
      500,
      500,
      500,
      500,
      500,
      500,
      500,
      500,
      500,
      500,
      500,
      500,
      500,
      500,
      500,
      500,
      500,
      500,
      500,
      500,
      500,
      500,
      500,
      500,
      500,
      500,
      500,
      500,
      500,
      500,
      500,
      500,
      500,
      500,
      500,
      500,
      500,
      500,
      500,
      500,
      500,
      500,
      500,
      500,
      500,
      500,
      500,
      500,
      500,
      500,
      500,
      500,
      500,
      500,
      500,
      500,
      500,
      500,
      500,
      500,
      500,
      500,
      500,
      500,
      500,
      500,
      500,
      500,
      500,
      500,
      500,
      500,
      500,
      500,
      500,
      500,
      500,
      500,
      500,
      500,
      500,
      500,
      500,
      500,
      500,
      500,
      500,
      500,
      500,
      500,
      500,
      500,
      500,
      500,
      500,
      500,
      500,
      500,
      500,
      500,
      500,
      500,
      500,
      500,
      500,
      500,
      500,
      500,
      500,
      500,
      500,
      500,
      500,
      500,
      500,
      500,
      500,
      500,
      500,
      500,
      500,
      500,
      500,
      500,
      500,
      500,
      500,
      500,
      500,
      500,
      500,
      500,
      500,
      500,
      500,
      500,
      500,
      500,
      500,
      500,
      500,
      500,
      500,
      500,
      500,
      500,
      500,
      500,
      500,
      500,
      500,
      500,
      500,
      500,
      500,
      500,
      500,
      500,
      500,
      500,
      500,
      500,
      500,
      500,
      500,
      500,
      500,
      500,
      500,
      500,
      500,
      500,
      500,
      500,
      500,
      500,
      500,
      500,
      500,
      500,
      500,
      500,
      500,
      500,
      500,
      500,
      500,
      500,
      500,
      500,
      500,
      500,
      500,
      500,
      500,
      500,
      500,
      500,
      500,
      500,
      500,
      500,
      500,
      500,
      500,
      500,
      500,
      500,
      500,
      500,
      500,
      500,
      500,
      500,
      500,
      500,
      500,
      500,
      500,
      500,
      500,
      500,
      500,
      500,
      500,
      500,
      500,
      500,
      500,
      500,
      500,
      500,
      500,
      500,
      500,
      500,
      500,
      500,
      500,
      500,
      500,
      500,
      500,
      500,
      500,
      500,
      500,
      500,
      500,
      500,
      500,
      500,
      500,
      500,
      500,
      500,
      500,
      500,
      500,
      500,
      500,
      500,
      500,
      500,
      500,
      500,
      500,
      500,
      500,
      500,
      500,
      500,
      500,
      500,
      500,
      500,
      500,
      500,
      500,
      500,
      500,
      500,
      500,
      500,
      500,
      500,
      500,
      500,
      500,
      500,
      500,
      500,
      500,
      500,
      500,
      500,
      500,
      500,
      500,
      500,
      500,
      500,
      500,
      500,
      500,
      500,
      500,
      500,
      500,
      500,
      500,
      500,
      500,
      500,
      500,
      500,
      500,
      500,
      500,
      500,
      500,
      500,
      500,
      500,
      500,
      500,
      500,
      500,
      500,
      500,
      500,
      500,
      500,
      500,
      500,
      500,
      500,
      500,
      500,
      500,
      500,
      500,
      500,
      500,
      500,
      500,
      500,
      500,
      500,
      500,
      500,
      500,
      500,
      500,
      500,
      500,
      500,
      500,
      500,
      500,
      500,
      500,
      500,
      500,
      500,
      500,
      500,
      500,
      500,
      500,
      500,
      500,
      500,
      500,
      500,
      500,
      500,
      500,
      500,
      500,
      500,
      500,
      500,
      500,
      500,
      500,
      500,
      500,
      500,
      500,
      500,
      500,
      500,
      500,
      500,
      500,
      500,
      500,
      500,
      500,
      500,
      500,
      500,
      500,
      500,
      500,
      500,
      500,
      500,
      500,
      500,
      500,
      500,
      500,
      500,
      500,
      500,
      500,
      500,
      500,
      500,
      500,
      500,
      500,
      500,
      500,
      500,
      500,
      500,
      500,
      500,
      500,
      500,
      500,
      500,
      500,
      500,
      500,
      500,
      500,
      500,
      500,
      500,
      500,
      500,
      500,
      500,
      500,
      500,
      500,
      500,
      500,
      500,
      500,
      500,
      500,
      500,
      500,
      500,
      500,
      500,
      500,
      500,
      500,
      500,
      500,
      500,
      500,
      500,
      500,
      500,
      500,
      500,
      500,
      500,
      500,
      500,
      500,
      500,
      500,
      500,
      500,
      500,
      500,
      500,
      500,
      500,
      500,
      500,
      500,
      500,
      500,
      500,
      500,
      500,
      500,
      500,
      500,
      500,
      500,
      500,
      500,
      500,
      500,
      500,
      500,
      500,
      500,
      500,
      500,
      500,
      500,
      500,
      500,
      500,
      500,
      500,
      500,
      500,
      500,
      500,
      500,
      500,
      500,
      500,
      500,
      500,
      500,
      500,
      500,
      500,
      500,
      500,
      500,
      500,
      500,
      500,
      500,
      500,
      500,
      500,
      500,
      500,
      500,
      500,
      500,
      500,
      500,
      500,
      500,
      500,
      500,
      500,
      500,
      500,
      500,
      500,
      500,
      500,
      500,
      500,
      500,
      500,
      500,
      500,
      500,
      500,
      500,
      500,
      500,
      500,
      500,
      500,
      500,
      500,
      500,
      500,
      500,
      500,
      500,
      500,
      500,
      500,
      500,
      500,
      500,
      500,
      500,
      500,
      500,
      500,
      500,
      500,
      500,
      500,
      500,
      500,
      500,
      500,
      500,
      500,
      500,
      500,
      500,
      500,
      500,
      500,
      500,
      500,
      500,
      500,
      500,
      500,
      500,
      500,
      500,
      500,
      500,
      500,
      500,
      500,
      500,
      500,
      500,
      500,
      500,
      500,
      500,
      500,
      500,
      500,
      500,
      500,
      500,
      500,
      500,
      500,
      500,
      500,
      500,
      500,
      500,
      500,
      500,
      500,
      500,
      500,
      500,
      500,
      500,
      500,
      500,
      500,
      500,
      500,
      500,
      500,
      500,
      500,
      500,
      500,
      500,
      500,
      500,
      500,
      500,
      500,
      500,
      500,
      500,
      500,
      500,
      500,
      500,
      500,
      500,
      500,
      500,
      500,
      500,
      500,
      500,
      500,
      500,
      500,
      500,
      500,
      500,
      500,
      500,
      500,
      500,
      500,
      500,
      500,
      500,
      500,
      500,
      500,
      500,
      500,
      500,
      500,
      500,
      500,
      500,
      500,
      500,
      500,
      500,
      500,
      500,
      500,
      500,
      500,
      500,
      500,
      500,
      500,
      500,
      500,
      500,
      500,
      500,
      500,
      500,
      500,
      500,
      500,
      500,
      500,
      500,
      500,
      500,
      500,
      500,
      500,
      500,
      500,
      500,
      500,
      500,
      500,
      500,
      500,
      500,
      500,
      500,
      500,
      500,
      500,
      500,
      500,
      500,
      500,
      500,
      500,
      500,
      500,
      500,
      500,
      500,
      500,
      500,
      500,
      500,
      500,
      500,
      500,
      500,
      500,
      500,
      500,
      500,
      500,
      500,
      500,
      500,
      500,
      500,
      500,
      500,
      500,
      500,
      500,
      500,
      500,
      500,
      500,
      500,
      500,
      500,
      500,
      500,
      500,
      500,
      500,
      500,
      500,
      500,
      500,
      500,
      500,
      500,
      500,
      500,
      500,
      500,
      500,
      500,
      500,
      500,
      500,
      500,
      500,
      500,
      500,
      500,
      500,
      500,
      500,
      500,
      500,
      500,
      500,
      500,
      500,
      500,
      500,
      500,
      500,
      500,
      500,
      500,
      500,
      500,
      500,
      500,
      500,
      500,
      500,
      500,
      500,
      500,
      500,
      500,
      500,
      500,
      500,
      500,
      500,
      500,
      500,
      500,
      500,
      500,
      500,
      500,
      500,
      500,
      500,
      500,
      500,
      500,
      500,
      500,
      500,
      500,
      500,
      500,
      500,
      500,
      500,
      500,
      500,
      500,
      500,
      500,
      500,
      500,
      500,
      500,
      500,
      500,
      500,
      500,
      500,
      500,
      500,
      500,
      500,
      500,
      500,
      500,
      500,
      500,
      500,
      500,
      500,
      500,
      500,
      500,
      500,
      500,
      500,
      500,
      500,
      500,
      500,
      500,
      500,
      500,
      500,
      500,
      500,
      500,
      500,
      500,
      500,
      500,
      500,
      500,
      500,
      500,
      500,
      500,
      500,
      500,
      500,
      500,
      500,
      500,
      500,
      500,
      500,
      500,
      500,
      500,
      500,
      500,
      500,
      500,
      500,
      500,
      500,
      500,
      500,
      500,
      500,
      500,
      500,
      500,
      500,
      500,
      500,
      500,
      500,
      500,
      500,
      500,
      500,
      500,
      500,
      500,
      500,
      500,
      500,
      500,
      500,
      500,
      500,
      500,
      500,
      500,
      500,
      500,
      500,
      500,
      500,
      500,
      500,
      500,
      500,
      500,
      500,
      500,
      500,
      500,
      500,
      500,
      500,
      500,
      500,
      500,
      500,
      500,
      500,
      500,
      500,
      500,
      500,
      500,
      500,
      500,
      500,
      500,
      500,
      500,
      500,
      500,
      500,
      500,
      500,
      500,
      500,
      500,
      500,
      500,
      500,
      500,
      500,
      500,
      500,
      500,
      500,
      500,
      500,
      500,
      500,
      500,
      500,
      500,
      500,
      500,
      500,
      500,
      500,
      500,
      500,
      500,
      500,
      500,
      500,
      500,
      500,
      500,
      500,
      500,
      500,
      500,
      500,
      500,
      500,
      500,
      500,
      500,
      500,
      500,
      500,
      500,
      500,
      500,
      500,
      500,
      500,
      500,
      500,
      500,
      500,
      500,
      500,
      500,
      500,
      500,
      500,
      500,
      500,
      500,
      500,
      500,
      500,
      500,
      500,
      500,
      500,
      500,
      500,
      500,
      500,
      500,
      500,
      500,
      500,
      500,
      500,
      500,
      500,
      500,
      500,
      500,
      500,
      500,
      500,
      500,
      500,
      500,
      500,
      500,
      500,
      500,
      500,
      500,
      500,
      500,
      500,
      500,
      500,
      500,
      500,
      500,
      500,
      500,
      500,
      500,
      500,
      500,
      500,
      500,
      500,
      500,
      500,
      500,
      500,
      500,
      500,
      500,
      500,
      500,
      500,
      500,
      500,
      500,
      500,
      500,
      500,
      500,
      500,
      500,
      500,
      500,
      500,
      500,
      500,
      500,
      500,
      500,
      500,
      500,
      500,
      500,
      500,
      500,
      500,
      500,
      500,
      500,
      500,
      500,
      500,
      500,
      500,
      500,
      500,
      500,
      500,
      500,
      500,
      500,
      500,
      500,
      500,
      500,
      500,
      500,
      500,
      500,
      500,
      500,
      500,
      500,
      500,
      500,
      500,
      500,
      500,
      500,
      500,
      500,
      500,
      500,
      500,
      500,
      500,
      500,
      500,
      500,
      500,
      500,
      500,
      500,
      500,
      500,
      500,
      500,
      500,
      500,
      500,
      500,
      500,
      500,
      500,
      500,
      500,
      500,
      500,
      500,
      500,
      500,
      500,
      500,
      500,
      500,
      500,
      500,
      500,
      500,
      500,
      500,
      500,
      500,
      500,
      500,
      500,
      500,
      500,
      500,
      500,
      500,
      500,
      500,
      500,
      500,
      500,
      500,
      500,
      500,
      500,
      500,
      500,
      500,
      500,
      500,
      500,
      500,
      500,
      500,
      500,
      500,
      500,
      500,
      500,
      500,
      500,
      500,
      500,
      500,
      500,
      500,
      500,
      500,
      500,
      500,
      500,
      500,
      500,
      500,
      500,
      500,
      500,
      500,
      500,
      500,
      500,
      500,
      500,
      500,
      500,
      500,
      500,
      500,
      500,
      500,
      500,
      500,
      500,
      500,
      500,
      500,
      500,
      500,
      500,
      500,
      500,
      500,
      500,
      500,
      500,
      500,
      500,
      500,
      500,
      500,
      500,
      500,
      500,
      500,
      500,
      500,
      500,
      500,
      500,
      500,
      500,
      500,
      500,
      500,
      500,
      500,
      500,
      500,
      500,
      500,
      500,
      500,
      500,
      500,
      500,
      500,
      500,
      500,
      500,
      500,
      500,
      500,
      500,
      500,
      500,
      500,
      500,
      500,
      500,
      500,
      500,
      500,
      500,
      500,
      500,
      500,
      500,
      500,
      500,
      500,
      500,
      500,
      500,
      500,
      500,
      500,
      500,
      500,
      500,
      500,
      500,
      500,
      500,
      500,
      500,
      500,
      500,
      500,
      500,
      500,
      500,
      500,
      500,
      500,
      500,
      500,
      500,
      500,
      500,
      500,
      500,
      500,
      500,
      500,
      500,
      500,
      500,
      500,
      500,
      500,
      500,
      500,
      500,
      500,
      500,
      500,
      500,
      500,
      500,
      500,
      500,
      500,
      500,
      500,
      500,
      500,
      500,
      500,
      500,
      500,
      500,
      500,
      500,
      500,
      500,
      500,
      500,
      500,
      500,
      500,
      500,
      500,
      500,
      500,
      500,
      500,
      500,
      500,
      500,
      500,
      500,
      500,
      500,
      500,
      500,
      500,
      500,
      500,
      500,
      500,
      500,
      500,
      500,
      500,
      500,
      500,
      500,
      500,
      500,
      500,
      500,
      500,
      500,
      500,
      500,
      500,
      500,
      500,
      500,
      500,
      500,
      500,
      500,
      500,
      500,
      500,
      500,
      500,
      500,
      500,
      500,
      500,
      500,
      500,
      500,
      500,
      500,
      500,
      500,
      500,
      500,
      500,
      500,
      500,
      500,
      500,
      500,
      500,
      500,
      500,
      500,
      500,
      500,
      500,
      500,
      500,
      500,
      500,
      500,
      500,
      500,
      500,
      500,
      500,
      500,
      500,
      500,
      500,
      500,
      500,
      500,
      500,
      500,
      500,
      500,
      500,
      500,
      500,
      500,
      500,
      500,
      500,
      500,
      500,
      500,
      500,
      500,
      500,
      500,
      500,
      500,
      500,
      500,
      500,
      500,
      500,
      500,
      500,
      500,
      500,
      500,
      500,
      500,
      500,
      500,
      500,
      500,
      500,
      500,
      500,
      500,
      500,
      500,
      500,
      500,
      500,
      500,
      500,
      500,
      500,
      500,
      500,
      500,
      500,
      500,
      500,
      500,
      500,
      500,
      500,
      500,
      500,
      500,
      500,
      500,
      500,
      500,
      500,
      500,
      500,
      500,
      500,
      500,
      500,
      500,
      500,
      500,
      500,
      500,
      500,
      500,
      500,
      500,
      500,
      500,
      500,
      500,
      500,
      500,
      500,
      500,
      500,
      500,
      500,
      500,
      500,
      500,
      500,
      500,
      500,
      500,
      500,
      500,
      500,
      500,
      500,
      500,
      500,
      500,
      500,
      500,
      500,
      500,
      500,
      500,
      500,
      500,
      500,
      500,
      500,
      500,
      500,
      500,
      500,
      500,
      500,
      500,
      500,
      500,
      500,
      500,
      500,
      500,
      500,
      500,
      500,
      500,
      500,
      500,
      500,
      500,
      500,
      500,
      500,
      500,
      500,
      500,
      500,
      500,
      500,
      500,
      500,
      500,
      500,
      500,
      500,
      500,
      500,
      500,
      500,
      500,
      500,
      500,
      500,
      500,
      500,
      500,
      500,
      500,
      500,
      500,
      500,
      500,
      500,
      500,
      500,
      500,
      500,
      500,
      500,
      500,
      500,
      500,
      500,
      500,
      500,
      500,
      500,
      500,
      500,
      500,
      500,
      500,
      500,
      500,
      500,
      500,
      500,
      500,
      500,
      500,
      500,
      500,
      500,
      500,
      500,
      500,
      500,
      500,
      500,
      500,
      500,
      500,
      500,
      500,
      500,
      500,
      500,
      500,
      500,
      500,
      500,
      500,
      500,
      500,
      500,
      500,
      500,
      500,
      500,
      500,
      500,
      500,
      500,
      500,
      500,
      500,
      500,
      500,
      500,
      500,
      500,
      500,
      500,
      500,
      500,
      500,
      500,
      500,
      500,
      500,
      500,
      500,
      500,
      500,
      500,
      500,
      500,
      500,
      500,
      500,
      500,
      500,
      500,
      500,
      500,
      500,
      500,
      500,
      500,
      500,
      500,
      500,
      500,
      500,
      500,
      500,
      500,
      500,
      500,
      500,
      500,
      500,
      500,
      500,
      500,
      500,
      500,
      500,
      500,
      500,
      500,
      500,
      500,
      500,
      500,
      500,
      500,
      500,
      500,
      500,
      500,
      500,
      500,
      500,
      500,
      500,
      500,
      500,
      500,
      500,
      500,
      500,
      500,
      500,
      500,
      500,
      500,
      500,
      500,
      500,
      500,
      500,
      500,
      500,
      500,
      500,
      500,
      500,
      500,
      500,
      500,
      500,
      500,
      500,
      500,
      500,
      500,
      500,
      500,
      500,
      500,
      500,
      500,
      500,
      500,
      500,
      500,
      500,
      500,
      500,
      500,
      500,
      500,
      500,
      500,
      500,
      500,
      500,
      500,
      500,
      500,
      500,
      500,
      500,
      500,
      500,
      500,
      500,
      500,
      500,
      500,
      500,
      500,
      500,
      500,
      500,
      500,
      500,
      500,
      500,
      500,
      500,
      500,
      500,
      500,
      500,
      500,
      500,
      500,
      500,
      500,
      500,
      500,
      500,
      500,
      500,
      500,
      500,
      500,
      500,
      500,
      500,
      500,
      500,
      500,
      500,
      500,
      500,
      500,
      500,
      500,
      500,
      500,
      500,
      500,
      500,
      500,
      500,
      500,
      500,
      500,
      500,
      500,
      500,
      500,
      500,
      500,
      500,
      500,
      500,
      500,
      500,
      500,
      500,
      500,
      500,
      500,
      500,
      500,
      500,
      500,
      500,
      500,
      500,
      500,
      500,
      500,
      500,
      500,
      500,
      500,
      500,
      500,
      500,
      500,
      500,
      500,
      500,
      500,
      500,
      500,
      500,
      500,
      500,
      500,
      500,
      500,
      500,
      500,
      500,
      500,
      500,
      500,
      500,
      500,
      500,
      500,
      500,
      500,
      500,
      500,
      500,
      500,
      500,
      500,
      500,
      500,
      500,
      500,
      500,
      500,
      500,
      500,
      500,
      500,
      500,
      500,
      500,
      500,
      500,
      500,
      500,
      500,
      500,
      500,
      500,
      500,
      500,
      500,
      500,
      500,
      500,
      500,
      500,
      500,
      500,
      500,
      500,
      500,
      500,
      500,
      500,
      500,
      500,
      500,
      500,
      500,
      500,
      500,
      500,
      500,
      500,
      500,
      500,
      500,
      500,
      500,
      500,
      500,
      500,
      500,
      500,
      500,
      500,
      500,
      500,
      500,
      500,
      500,
      500,
      500,
      500,
      500,
      500,
      500,
      500,
      500,
      500,
      500,
      500,
      500,
      500,
      500,
      500,
      500,
      500,
      500,
      500,
      500,
      500,
      500,
      500,
      500,
      500,
      500,
      500,
      500,
      500,
      500,
      500,
      500,
      500,
      500,
      500,
      500,
      500,
      500,
      500,
      500,
      500,
      500,
      500,
      500,
      500,
      500,
      500,
      500,
      500,
      500,
      500,
      500,
      500,
      500,
      500,
      500,
      500,
      500,
      500,
      500,
      500,
      500,
      500,
      500,
      500,
      500,
      500,
      500,
      500,
      500,
      500,
      500,
      500,
      500,
      500,
      500,
      500,
      500,
      500,
      500,
      500,
      500,
      500,
      500,
      500,
      500,
      500,
      500,
      500,
      500,
      500,
      500,
      500,
      500,
      500,
      500,
      500,
      500,
      500,
      500,
      500,
      500,
      500,
      500,
      500,
      500,
      500,
      500,
      500,
      500,
      500,
      500,
      500,
      500,
      500,
      500,
      500,
      500,
      500,
      500,
      500,
      500,
      500,
      500,
      500,
      500,
      500,
      500,
      500,
      500,
      500,
      500,
      500,
      500,
      500,
      500,
      500,
      500,
      500,
      500,
      500,
      500,
      500,
      500,
      500,
      500,
      500,
      500,
      500,
      500,
      500,
      500,
      500,
      500,
      500,
      500,
      500,
      500,
      500,
      500,
      500,
      500,
      500,
      500,
      500,
      500,
      500,
      500,
      500,
      500,
      500,
      500,
      500,
      500,
      500
    ],
    "config": {
      "discount_factor": 0.95,
      "learning_rate": 0.0003,
      "batch_size": 256,
      "buffer_size": 100000,
      "learning_starts": 1000,
      "train_freq": 1,
      "gradient_steps": 1,
      "tau": 0.005,
      "ent_coef": "auto",
      "target_entropy": null,
      "hidden_dim": 128,
      "gradient_clip_norm": 1.0,
      "reward_clip": 10.0,
      "seed": 12347
    },
    "test_rewards": [
      -762.0,
      1232.0,
      1013.0,
      1410.0,
      1306.0,
      1388.0,
      751.0,
      1118.0,
      71.0,
      737.0,
      -4565.0,
      737.0,
      2021.0,
      -773.0,
      1883.0,
      586.0,
      30.0,
      1531.0,
      882.0,
      997.0,
      1217.0,
      808.0,
      588.0,
      1175.0,
      813.0,
      1754.0,
      1112.0,
      -59468.0,
      1555.0,
      -184.0,
      1082.0,
      1286.0,
      900.0,
      1538.0,
      737.0,
      1332.0,
      -1934.0,
      87.0,
      1325.0,
      965.0,
      990.0,
      1507.0,
      778.0,
      707.0,
      -331.0,
      1431.0,
      1191.0,
      1652.0,
      1412.0,
      1089.0
    ],
    "test_steps": [
      500,
      500,
      500,
      500,
      500,
      500,
      500,
      500,
      500,
      500,
      500,
      500,
      500,
      500,
      500,
      500,
      500,
      500,
      500,
      500,
      500,
      500,
      500,
      500,
      500,
      500,
      500,
      500,
      500,
      500,
      500,
      500,
      500,
      500,
      500,
      500,
      500,
      500,
      500,
      500,
      500,
      500,
      500,
      500,
      500,
      500,
      500,
      500,
      500,
      500
    ],
    "test_mean": -425.86,
    "test_std": 8499.91964670255,
    "runtime_seconds": {
      "training": 20448.723363439996,
      "evaluation": 20.498958739000955,
      "total": 20469.232681589
    }
  }
}